Metadata-Version: 2.1
Name: racegame2d
Version: 0.1.0
Summary: 2D racing games in python based on PyGame2
Author: Christoph Hoeppke
